Metadata-Version: 1.0
Name: jhashcode-python3
Version: 0.4
Summary: Python implemented Java `hashCode` methods.
Home-page: https://github.com/neuront/pyjhashcode
Author: Neuron Teckid
Author-email: lene13@gmail.com
License: MIT
Keywords: Java hashCode
Platform: UNKNOWN
